IAMPASS/__init__.py
IAMPASS/authentication_api.py
IAMPASS/authentication_method.py
IAMPASS/config.py
IAMPASS/hmac.py
IAMPASS/management_api.py
IAMPASS/session.py
IAMPASS/status.py
IAMPASS-0.0.10.dist-info/LICENSE
IAMPASS-0.0.10.dist-info/METADATA
IAMPASS-0.0.10.dist-info/WHEEL
IAMPASS-0.0.10.dist-info/top_level.txt
IAMPASS-0.0.10.dist-info/RECORD
