Metadata-Version: 2.1
Name: IAMPASS
Version: 0.0.10
Summary: Python package to access IAMPASS API
Author: IAMPASS
Author-email: support@iampass.com
License: UNKNOWN
Platform: UNKNOWN
Classifier: Programming Language :: Python :: 3
Classifier: License :: OSI Approved :: MIT License
Classifier: Operating System :: OS Independent
Requires-Python: >=3.6
License-File: LICENSE
Requires-Dist: marshmallow-dataclass
Requires-Dist: marshmallow-enum
